balance/__init__.py
balance/adjustment.py
balance/balancedf_class.py
balance/cli.py
balance/csv_utils.py
balance/sample_class.py
balance/testutil.py
balance/typing.py
balance/util.py
balance/datasets/__init__.py
balance/datasets/sim_data_cbps.R
balance/datasets/sim_data_cbps.csv
balance/stats_and_plots/__init__.py
balance/stats_and_plots/general_stats.py
balance/stats_and_plots/weighted_comparisons_plots.py
balance/stats_and_plots/weighted_comparisons_stats.py
balance/stats_and_plots/weighted_stats.py
balance/stats_and_plots/weights_stats.py
balance/utils/__init__.py
balance/utils/data_transformation.py
balance/utils/file_utils.py
balance/utils/input_validation.py
balance/utils/logging_utils.py
balance/utils/model_matrix.py
balance/utils/pandas_utils.py
balance/weighting_methods/__init__.py
balance/weighting_methods/adjust_null.py
balance/weighting_methods/cbps.py
balance/weighting_methods/ipw.py
balance/weighting_methods/poststratify.py
balance/weighting_methods/rake.py
balance-0.15.0.dist-info/licenses/LICENSE
balance-0.15.0.dist-info/licenses/LICENSE-DOCUMENTATION
balance-0.15.0.dist-info/METADATA
balance-0.15.0.dist-info/WHEEL
balance-0.15.0.dist-info/top_level.txt
balance-0.15.0.dist-info/RECORD
