Metadata-Version: 2.4
Name: balance
Version: 0.15.0
Summary: balance is a Python package offering a simple workflow and methods for dealing with biased data samples when looking to infer from them to some target population of interest.
Home-page: https://github.com/facebookresearch/balance
Author: Facebook, Inc.
License: MIT License
Project-URL: homepage, https://import-balance.org/
Project-URL: repository, https://github.com/facebookresearch/balance
Project-URL: changelog, https://github.com/facebookresearch/balance/blob/main/CHANGELOG.md
Keywords: balance,statistics,bias
Classifier: Development Status :: 4 - Beta
Classifier: Intended Audience :: Science/Research
Classifier: Topic :: Scientific/Engineering
Classifier: Programming Language :: Python :: 3
Classifier: Programming Language :: Python :: 3.9
Classifier: Programming Language :: Python :: 3.10
Classifier: Programming Language :: Python :: 3.11
Classifier: Programming Language :: Python :: 3.12
Classifier: Programming Language :: Python :: 3.13
Classifier: Programming Language :: Python :: 3.14
Requires-Python: >=3.9
License-File: LICENSE
License-File: LICENSE-DOCUMENTATION
Requires-Dist: numpy<2.0,>=1.21.0; python_version < "3.12"
Requires-Dist: numpy>=1.24.0; python_version >= "3.12"
Requires-Dist: pandas<2.4.0,>=1.5.0; python_version < "3.12"
Requires-Dist: pandas>=2.0.0; python_version >= "3.12"
Requires-Dist: scipy<1.14.0,>=1.7.0; python_version < "3.12"
Requires-Dist: scipy>=1.11.0; python_version >= "3.12"
Requires-Dist: scikit-learn<1.4.0,>=1.0.0; python_version < "3.12"
Requires-Dist: scikit-learn>=1.3.0; python_version >= "3.12"
Requires-Dist: ipython
Requires-Dist: patsy
Requires-Dist: seaborn
Requires-Dist: plotly
Requires-Dist: matplotlib
Requires-Dist: statsmodels
Requires-Dist: session-info
Provides-Extra: dev
Requires-Dist: setuptools_scm; extra == "dev"
Requires-Dist: wheel; extra == "dev"
Requires-Dist: pytest; extra == "dev"
Requires-Dist: pytest-cov; extra == "dev"
Requires-Dist: coverage; extra == "dev"
Requires-Dist: sphinx; extra == "dev"
Requires-Dist: notebook; extra == "dev"
Requires-Dist: nbconvert; extra == "dev"
Requires-Dist: pre-commit; extra == "dev"
Dynamic: home-page
Dynamic: license-file
Dynamic: requires-python
